alert.py
bigquery/__init__.py
bigquery/bigquery.py
bigquery/bq_query_runner.py
dbt_artifact_parser-1.0.5.data/scripts/dbt-artifact-parser
dbt_artifact_parser-1.0.5.data/scripts/exec
dbt_utils/dbt_runner.py
message/__init__.py
message/builder.py
parsers/__init__.py
parsers/manifest.py
parsers/manifest_parser.py
parsers/parse_run_results.py
parsers/run_result.py
slack/__init__.py
slack/client.py
dbt_artifact_parser-1.0.5.dist-info/LICENSE
dbt_artifact_parser-1.0.5.dist-info/METADATA
dbt_artifact_parser-1.0.5.dist-info/WHEEL
dbt_artifact_parser-1.0.5.dist-info/top_level.txt
dbt_artifact_parser-1.0.5.dist-info/RECORD
